.coveragerc
.editorconfig
.gitignore
.travis.yml
Dockerfile
LICENSE
Makefile
README.md
docker-compose.yml
pyproject.toml
requirements.txt
requirements_dev.txt
setup.cfg
setup.py
.github/workflows/python-publish.yml
democritus_dates/__init__.py
democritus_dates/dates_and_times.py
democritus_dates/dates_and_times_temp_utils.py
democritus_dates.egg-info/PKG-INFO
democritus_dates.egg-info/SOURCES.txt
democritus_dates.egg-info/dependency_links.txt
democritus_dates.egg-info/requires.txt
democritus_dates.egg-info/top_level.txt
democritus_dates.egg-info/zip-safe
tests/__init__.py
tests/test_dates_and_times.py